bed_lookup/__init__.py
bed_lookup/_bed_lookup.cpp
bed_lookup/_bed_lookup.cpython-39-darwin.so
bed_lookup/logme.py
bed_lookup-1.5.data/scripts/bed_location_lookup
bed_lookup-1.5.dist-info/LICENSE
bed_lookup-1.5.dist-info/METADATA
bed_lookup-1.5.dist-info/WHEEL
bed_lookup-1.5.dist-info/top_level.txt
bed_lookup-1.5.dist-info/RECORD
